{
  "4h_candles": [
    {
      "timestamp": "2025-12-15 09:30-13:00",
      "date": "2025-12-15",
      "period": "morning",
      "open": 685.74,
      "high": 685.76,
      "low": 679.25,
      "close": 680.5044,
      "volume": 48359091
    },
    {
      "timestamp": "2025-12-15 13:00-16:00",
      "date": "2025-12-15",
      "period": "afternoon",
      "open": 680.5,
      "high": 681.78,
      "low": 679.51,
      "close": 680.7,
      "volume": 33165802
    },
    {
      "timestamp": "2025-12-16 09:30-13:00",
      "date": "2025-12-16",
      "period": "morning",
      "open": 679.23,
      "high": 681.08,
      "low": 675.42,
      "close": 675.6,
      "volume": 41198696
    },
    {
      "timestamp": "2025-12-16 13:00-16:00",
      "date": "2025-12-16",
      "period": "afternoon",
      "open": 675.61,
      "high": 680.56,
      "low": 674.98,
      "close": 678.86,
      "volume": 47672312
    },
    {
      "timestamp": "2025-12-17 09:30-13:00",
      "date": "2025-12-17",
      "period": "morning",
      "open": 679.89,
      "high": 680.435,
      "low": 673.0,
      "close": 673.8,
      "volume": 45835738
    },
    {
      "timestamp": "2025-12-17 13:00-16:00",
      "date": "2025-12-17",
      "period": "afternoon",
      "open": 673.81,
      "high": 674.8765,
      "low": 671.195,
      "close": 671.3,
      "volume": 44568077
    },
    {
      "timestamp": "2025-12-18 09:30-13:00",
      "date": "2025-12-18",
      "period": "morning",
      "open": 677.6,
      "high": 680.74,
      "low": 674.9,
      "close": 678.37,
      "volume": 53341403
    },
    {
      "timestamp": "2025-12-18 13:00-16:00",
      "date": "2025-12-18",
      "period": "afternoon",
      "open": 678.36,
      "high": 679.7,
      "low": 675.32,
      "close": 676.48,
      "volume": 43682711
    },
    {
      "timestamp": "2025-12-19 09:30-13:00",
      "date": "2025-12-19",
      "period": "morning",
      "open": 676.59,
      "high": 681.058,
      "low": 676.47,
      "close": 680.655,
      "volume": 48754740
    },
    {
      "timestamp": "2025-12-19 13:00-16:00",
      "date": "2025-12-19",
      "period": "afternoon",
      "open": 680.655,
      "high": 681.09,
      "low": 679.61,
      "close": 680.59,
      "volume": 35998050
    },
    {
      "timestamp": "2025-12-22 09:30-13:00",
      "date": "2025-12-22",
      "period": "morning",
      "open": 683.94,
      "high": 685.36,
      "low": 682.68,
      "close": 685.21,
      "volume": 28599534
    },
    {
      "timestamp": "2025-12-22 13:00-16:00",
      "date": "2025-12-22",
      "period": "afternoon",
      "open": 685.21,
      "high": 685.22,
      "low": 680.5868,
      "close": 684.79,
      "volume": 26308083
    },
    {
      "timestamp": "2025-12-23 09:30-13:00",
      "date": "2025-12-23",
      "period": "morning",
      "open": 683.92,
      "high": 687.22,
      "low": 683.87,
      "close": 686.985,
      "volume": 30174975
    },
    {
      "timestamp": "2025-12-23 13:00-16:00",
      "date": "2025-12-23",
      "period": "afternoon",
      "open": 686.99,
      "high": 688.2,
      "low": 686.92,
      "close": 687.91,
      "volume": 25198112
    },
    {
      "timestamp": "2025-12-24 09:30-13:00",
      "date": "2025-12-24",
      "period": "morning",
      "open": 687.95,
      "high": 690.83,
      "low": 687.8,
      "close": 690.28,
      "volume": 33994510
    },
    {
      "timestamp": "2025-12-24 13:00-16:00",
      "date": "2025-12-24",
      "period": "afternoon",
      "open": 690.29,
      "high": 690.38,
      "low": 689.75,
      "close": 689.87,
      "volume": 3181302
    },
    {
      "timestamp": "2025-12-26 09:30-13:00",
      "date": "2025-12-26",
      "period": "morning",
      "open": 690.64,
      "high": 691.66,
      "low": 689.39,
      "close": 689.79,
      "volume": 21095774
    },
    {
      "timestamp": "2025-12-26 13:00-16:00",
      "date": "2025-12-26",
      "period": "afternoon",
      "open": 689.79,
      "high": 690.5,
      "low": 689.27,
      "close": 690.25,
      "volume": 16313051
    },
    {
      "timestamp": "2025-12-29 09:30-13:00",
      "date": "2025-12-29",
      "period": "morning",
      "open": 687.54,
      "high": 689.2,
      "low": 686.07,
      "close": 686.99,
      "volume": 23911780
    },
    {
      "timestamp": "2025-12-29 13:00-16:00",
      "date": "2025-12-29",
      "period": "afternoon",
      "open": 686.99,
      "high": 688.62,
      "low": 686.79,
      "close": 687.84,
      "volume": 28401714
    },
    {
      "timestamp": "2025-12-30 09:30-13:00",
      "date": "2025-12-30",
      "period": "morning",
      "open": 687.445,
      "high": 688.555,
      "low": 686.58,
      "close": 687.635,
      "volume": 19942236
    },
    {
      "timestamp": "2025-12-30 13:00-16:00",
      "date": "2025-12-30",
      "period": "afternoon",
      "open": 687.635,
      "high": 687.94,
      "low": 686.7,
      "close": 686.94,
      "volume": 20106543
    },
    {
      "timestamp": "2025-12-31 09:30-13:00",
      "date": "2025-12-31",
      "period": "morning",
      "open": 687.14,
      "high": 687.36,
      "low": 684.18,
      "close": 684.805,
      "volume": 26563893
    },
    {
      "timestamp": "2025-12-31 13:00-16:00",
      "date": "2025-12-31",
      "period": "afternoon",
      "open": 684.8,
      "high": 686.24,
      "low": 681.71,
      "close": 681.84,
      "volume": 33787525
    },
    {
      "timestamp": "2026-01-02 09:30-13:00",
      "date": "2026-01-02",
      "period": "morning",
      "open": 685.71,
      "high": 686.87,
      "low": 680.28,
      "close": 681.18,
      "volume": 48097506
    },
    {
      "timestamp": "2026-01-02 13:00-16:00",
      "date": "2026-01-02",
      "period": "afternoon",
      "open": 681.18,
      "high": 683.95,
      "low": 679.82,
      "close": 683.17,
      "volume": 32619370
    },
    {
      "timestamp": "2026-01-05 09:30-13:00",
      "date": "2026-01-05",
      "period": "morning",
      "open": 686.54,
      "high": 689.43,
      "low": 686.375,
      "close": 688.58,
      "volume": 36749085
    },
    {
      "timestamp": "2026-01-05 13:00-16:00",
      "date": "2026-01-05",
      "period": "afternoon",
      "open": 688.57,
      "high": 688.775,
      "low": 687.16,
      "close": 687.73,
      "volume": 26605095
    },
    {
      "timestamp": "2026-01-06 09:30-13:00",
      "date": "2026-01-06",
      "period": "morning",
      "open": 687.93,
      "high": 691.1,
      "low": 687.78,
      "close": 690.945,
      "volume": 36700026
    },
    {
      "timestamp": "2026-01-06 13:00-16:00",
      "date": "2026-01-06",
      "period": "afternoon",
      "open": 690.95,
      "high": 692.315,
      "low": 690.55,
      "close": 691.8,
      "volume": 25773459
    }
  ],
  "atr_values": [
    {
      "timestamp": "2025-12-24 09:30-13:00",
      "date": "2025-12-24",
      "period": "morning",
      "atr": 4.398407142857146,
      "close": 690.28
    },
    {
      "timestamp": "2025-12-24 13:00-16:00",
      "date": "2025-12-24",
      "period": "afternoon",
      "atr": 4.129235204081636,
      "close": 689.87
    },
    {
      "timestamp": "2025-12-26 09:30-13:00",
      "date": "2025-12-26",
      "period": "morning",
      "atr": 3.9964326895043745,
      "close": 689.79
    },
    {
      "timestamp": "2025-12-26 13:00-16:00",
      "date": "2025-12-26",
      "period": "afternoon",
      "atr": 3.7988303545397777,
      "close": 690.25
    },
    {
      "timestamp": "2025-12-29 09:30-13:00",
      "date": "2025-12-29",
      "period": "morning",
      "atr": 3.8260567577869327,
      "close": 686.99
    },
    {
      "timestamp": "2025-12-29 13:00-16:00",
      "date": "2025-12-29",
      "period": "afternoon",
      "atr": 3.683481275087869,
      "close": 687.84
    },
    {
      "timestamp": "2025-12-30 09:30-13:00",
      "date": "2025-12-30",
      "period": "morning",
      "atr": 3.561446898295872,
      "close": 687.635
    },
    {
      "timestamp": "2025-12-30 13:00-16:00",
      "date": "2025-12-30",
      "period": "afternoon",
      "atr": 3.3956292627033102,
      "close": 686.94
    },
    {
      "timestamp": "2025-12-31 09:30-13:00",
      "date": "2025-12-31",
      "period": "morning",
      "atr": 3.3802271725102213,
      "close": 684.805
    },
    {
      "timestamp": "2025-12-31 13:00-16:00",
      "date": "2025-12-31",
      "period": "afternoon",
      "atr": 3.4623538030452035,
      "close": 681.84
    },
    {
      "timestamp": "2026-01-02 09:30-13:00",
      "date": "2026-01-02",
      "period": "morning",
      "atr": 3.685757102827691,
      "close": 681.18
    },
    {
      "timestamp": "2026-01-02 13:00-16:00",
      "date": "2026-01-02",
      "period": "afternoon",
      "atr": 3.7174887383399984,
      "close": 683.17
    },
    {
      "timestamp": "2026-01-05 09:30-13:00",
      "date": "2026-01-05",
      "period": "morning",
      "atr": 3.899096685601426,
      "close": 688.58
    },
    {
      "timestamp": "2026-01-05 13:00-16:00",
      "date": "2026-01-05",
      "period": "afternoon",
      "atr": 3.735946922344182,
      "close": 687.73
    },
    {
      "timestamp": "2026-01-06 09:30-13:00",
      "date": "2026-01-06",
      "period": "morning",
      "atr": 3.7098078564624553,
      "close": 690.945
    },
    {
      "timestamp": "2026-01-06 13:00-16:00",
      "date": "2026-01-06",
      "period": "afternoon",
      "atr": 3.5708930095722873,
      "close": 691.8
    }
  ],
  "current_levels": {
    "update_type": "1PM_update",
    "timestamp": "2026-01-07T13:43:09.260014-05:00",
    "prior_4h_close": 690.945,
    "current_atr": 3.5708930095722873,
    "levels": {
      "Level_+1.0": 694.5158930095723,
      "Level_-1.0": 687.3741069904278,
      "Level_+0.786": 693.7517219055238,
      "Level_-0.786": 688.1382780944763,
      "Level_+0.618": 693.1518118799157,
      "Level_-0.618": 688.7381881200844,
      "Level_+0.5": 692.7304465047862,
      "Level_-0.5": 689.1595534952139,
      "Level_+0.382": 692.3090811296566,
      "Level_-0.382": 689.5809188703435,
      "Level_+0.236": 691.7877307502591,
      "Level_-0.236": 690.102269249741,
      "Level_0": 690.945
    }
  }
}