{
  "4h_candles": [
    {
      "timestamp": "2025-07-02 09:30-13:00",
      "date": "2025-07-02",
      "period": "morning",
      "open": 617.24,
      "high": 619.6011,
      "low": 616.61,
      "close": 619.585,
      "volume": 29561820
    },
    {
      "timestamp": "2025-07-02 13:00-16:00",
      "date": "2025-07-02",
      "period": "afternoon",
      "open": 619.58,
      "high": 620.49,
      "low": 619.12,
      "close": 620.39,
      "volume": 27939590
    },
    {
      "timestamp": "2025-07-03 09:30-13:00",
      "date": "2025-07-03",
      "period": "morning",
      "open": 622.45,
      "high": 626.28,
      "low": 622.43,
      "close": 625.35,
      "volume": 43410837
    },
    {
      "timestamp": "2025-07-03 13:00-16:00",
      "date": "2025-07-03",
      "period": "afternoon",
      "open": 625.35,
      "high": 625.72,
      "low": 624.5,
      "close": 625.13,
      "volume": 4853459
    },
    {
      "timestamp": "2025-07-07 09:30-13:00",
      "date": "2025-07-07",
      "period": "morning",
      "open": 623.36,
      "high": 624.03,
      "low": 619.241,
      "close": 619.8006,
      "volume": 31564261
    },
    {
      "timestamp": "2025-07-07 13:00-16:00",
      "date": "2025-07-07",
      "period": "afternoon",
      "open": 619.78,
      "high": 621.41,
      "low": 617.87,
      "close": 620.78,
      "volume": 35782376
    },
    {
      "timestamp": "2025-07-08 09:30-13:00",
      "date": "2025-07-08",
      "period": "morning",
      "open": 621.35,
      "high": 622.11,
      "low": 619.52,
      "close": 620.7999,
      "volume": 30014301
    },
    {
      "timestamp": "2025-07-08 13:00-16:00",
      "date": "2025-07-08",
      "period": "afternoon",
      "open": 620.79,
      "high": 621.31,
      "low": 619.84,
      "close": 620.31,
      "volume": 25150258
    },
    {
      "timestamp": "2025-07-09 09:30-13:00",
      "date": "2025-07-09",
      "period": "morning",
      "open": 622.77,
      "high": 624.72,
      "low": 620.9105,
      "close": 622.02,
      "volume": 32348858
    },
    {
      "timestamp": "2025-07-09 13:00-16:00",
      "date": "2025-07-09",
      "period": "afternoon",
      "open": 622.01,
      "high": 624.21,
      "low": 621.62,
      "close": 624.03,
      "volume": 26489367
    },
    {
      "timestamp": "2025-07-10 09:30-13:00",
      "date": "2025-07-10",
      "period": "morning",
      "open": 624.2,
      "high": 625.785,
      "low": 623.01,
      "close": 625.54,
      "volume": 27482572
    },
    {
      "timestamp": "2025-07-10 13:00-16:00",
      "date": "2025-07-10",
      "period": "afternoon",
      "open": 625.54,
      "high": 626.8701,
      "low": 625.21,
      "close": 625.84,
      "volume": 24456357
    },
    {
      "timestamp": "2025-07-11 09:30-13:00",
      "date": "2025-07-11",
      "period": "morning",
      "open": 622.74,
      "high": 624.64,
      "low": 621.53,
      "close": 624.3458,
      "volume": 28701375
    },
    {
      "timestamp": "2025-07-11 13:00-16:00",
      "date": "2025-07-11",
      "period": "afternoon",
      "open": 624.35,
      "high": 624.86,
      "low": 623.13,
      "close": 623.61,
      "volume": 28817757
    },
    {
      "timestamp": "2025-07-14 09:30-13:00",
      "date": "2025-07-14",
      "period": "morning",
      "open": 623.16,
      "high": 624.48,
      "low": 621.7999,
      "close": 624.28,
      "volume": 25966775
    },
    {
      "timestamp": "2025-07-14 13:00-16:00",
      "date": "2025-07-14",
      "period": "afternoon",
      "open": 624.285,
      "high": 625.1581,
      "low": 624.28,
      "close": 624.74,
      "volume": 20910049
    },
    {
      "timestamp": "2025-07-15 09:30-13:00",
      "date": "2025-07-15",
      "period": "morning",
      "open": 627.52,
      "high": 627.86,
      "low": 623.01,
      "close": 623.22,
      "volume": 34729397
    },
    {
      "timestamp": "2025-07-15 13:00-16:00",
      "date": "2025-07-15",
      "period": "afternoon",
      "open": 623.22,
      "high": 624.87,
      "low": 622.075,
      "close": 622.12,
      "volume": 31451642
    },
    {
      "timestamp": "2025-07-16 09:30-13:00",
      "date": "2025-07-16",
      "period": "morning",
      "open": 623.74,
      "high": 624.12,
      "low": 618.05,
      "close": 623.1048,
      "volume": 59631030
    },
    {
      "timestamp": "2025-07-16 13:00-16:00",
      "date": "2025-07-16",
      "period": "afternoon",
      "open": 623.1,
      "high": 624.73,
      "low": 622.72,
      "close": 624.18,
      "volume": 23154964
    },
    {
      "timestamp": "2025-07-17 09:30-13:00",
      "date": "2025-07-17",
      "period": "morning",
      "open": 624.4,
      "high": 627.51,
      "low": 624.18,
      "close": 626.83,
      "volume": 28507269
    },
    {
      "timestamp": "2025-07-17 13:00-16:00",
      "date": "2025-07-17",
      "period": "afternoon",
      "open": 626.83,
      "high": 628.4048,
      "low": 626.665,
      "close": 627.98,
      "volume": 31790841
    },
    {
      "timestamp": "2025-07-18 09:30-13:00",
      "date": "2025-07-18",
      "period": "morning",
      "open": 629.3,
      "high": 629.47,
      "low": 626.48,
      "close": 626.68,
      "volume": 34398321
    },
    {
      "timestamp": "2025-07-18 13:00-16:00",
      "date": "2025-07-18",
      "period": "afternoon",
      "open": 626.67,
      "high": 627.76,
      "low": 626.46,
      "close": 627.58,
      "volume": 19512634
    },
    {
      "timestamp": "2025-07-21 09:30-13:00",
      "date": "2025-07-21",
      "period": "morning",
      "open": 628.77,
      "high": 631.54,
      "low": 628.67,
      "close": 631.25,
      "volume": 25937486
    },
    {
      "timestamp": "2025-07-21 13:00-16:00",
      "date": "2025-07-21",
      "period": "afternoon",
      "open": 631.25,
      "high": 631.52,
      "low": 628.34,
      "close": 628.76,
      "volume": 30064986
    },
    {
      "timestamp": "2025-07-22 09:30-13:00",
      "date": "2025-07-22",
      "period": "morning",
      "open": 629.1,
      "high": 629.19,
      "low": 626.19,
      "close": 627.855,
      "volume": 28733782
    },
    {
      "timestamp": "2025-07-22 13:00-16:00",
      "date": "2025-07-22",
      "period": "afternoon",
      "open": 627.86,
      "high": 629.73,
      "low": 627.52,
      "close": 628.83,
      "volume": 25670634
    },
    {
      "timestamp": "2025-07-23 09:30-13:00",
      "date": "2025-07-23",
      "period": "morning",
      "open": 631.55,
      "high": 632.79,
      "low": 629.73,
      "close": 631.86,
      "volume": 30169745
    },
    {
      "timestamp": "2025-07-23 13:00-16:00",
      "date": "2025-07-23",
      "period": "afternoon",
      "open": 631.86,
      "high": 634.16,
      "low": 631.525,
      "close": 634.16,
      "volume": 31521967
    }
  ],
  "atr_values": [
    {
      "timestamp": "2025-07-14 09:30-13:00",
      "date": "2025-07-14",
      "period": "morning",
      "atr": 3.008871428571435,
      "close": 624.28
    },
    {
      "timestamp": "2025-07-14 13:00-16:00",
      "date": "2025-07-14",
      "period": "afternoon",
      "atr": 2.8566734693877622,
      "close": 624.74
    },
    {
      "timestamp": "2025-07-15 09:30-13:00",
      "date": "2025-07-15",
      "period": "morning",
      "atr": 2.9990539358600663,
      "close": 623.22
    },
    {
      "timestamp": "2025-07-15 13:00-16:00",
      "date": "2025-07-15",
      "period": "afternoon",
      "atr": 2.9844786547272015,
      "close": 622.12
    },
    {
      "timestamp": "2025-07-16 09:30-13:00",
      "date": "2025-07-16",
      "period": "morning",
      "atr": 3.2048730365324047,
      "close": 623.1048
    },
    {
      "timestamp": "2025-07-16 13:00-16:00",
      "date": "2025-07-16",
      "period": "afternoon",
      "atr": 3.119524962494375,
      "close": 624.18
    },
    {
      "timestamp": "2025-07-17 09:30-13:00",
      "date": "2025-07-17",
      "period": "morning",
      "atr": 3.13455889374478,
      "close": 626.83
    },
    {
      "timestamp": "2025-07-17 13:00-16:00",
      "date": "2025-07-17",
      "period": "afternoon",
      "atr": 3.0349332584773,
      "close": 627.98
    },
    {
      "timestamp": "2025-07-18 09:30-13:00",
      "date": "2025-07-18",
      "period": "morning",
      "atr": 3.0317237400146366,
      "close": 626.68
    },
    {
      "timestamp": "2025-07-18 13:00-16:00",
      "date": "2025-07-18",
      "period": "afternoon",
      "atr": 2.908029187156445,
      "close": 627.58
    },
    {
      "timestamp": "2025-07-21 09:30-13:00",
      "date": "2025-07-21",
      "period": "morning",
      "atr": 2.983169959502408,
      "close": 631.25
    },
    {
      "timestamp": "2025-07-21 13:00-16:00",
      "date": "2025-07-21",
      "period": "afternoon",
      "atr": 2.997229248109375,
      "close": 628.76
    },
    {
      "timestamp": "2025-07-22 09:30-13:00",
      "date": "2025-07-22",
      "period": "morning",
      "atr": 2.9974271589587054,
      "close": 627.855
    },
    {
      "timestamp": "2025-07-22 13:00-16:00",
      "date": "2025-07-22",
      "period": "afternoon",
      "atr": 2.941182361890229,
      "close": 628.83
    },
    {
      "timestamp": "2025-07-23 09:30-13:00",
      "date": "2025-07-23",
      "period": "morning",
      "atr": 3.0139550503266355,
      "close": 631.86
    },
    {
      "timestamp": "2025-07-23 13:00-16:00",
      "date": "2025-07-23",
      "period": "afternoon",
      "atr": 2.9868868324461606,
      "close": 634.16
    }
  ],
  "current_levels": {
    "update_type": "4PM_update",
    "timestamp": "2025-07-24T14:39:31.890508-04:00",
    "prior_4h_close": 634.16,
    "current_atr": 2.9868868324461606,
    "levels": {
      "Level_+1.0": 637.1468868324462,
      "Level_-1.0": 631.1731131675538,
      "Level_+0.786": 636.5076930503027,
      "Level_-0.786": 631.8123069496972,
      "Level_+0.618": 636.0058960624517,
      "Level_-0.618": 632.3141039375482,
      "Level_+0.5": 635.653443416223,
      "Level_-0.5": 632.6665565837769,
      "Level_+0.382": 635.3009907699944,
      "Level_-0.382": 633.0190092300055,
      "Level_+0.236": 634.8649052924573,
      "Level_-0.236": 633.4550947075427,
      "Level_0": 634.16
    }
  }
}